README.rst
setup.py
urlclustering/__init__.py
urlclustering/parsedurl.py
urlclustering/reimprover.py
urlclustering/urlclusterer.py
urlclustering/urltree.py
urlclustering.egg-info/PKG-INFO
urlclustering.egg-info/SOURCES.txt
urlclustering.egg-info/dependency_links.txt
urlclustering.egg-info/top_level.txt