Metadata-Version: 1.1
Name: urlclustering
Version: 0.4.1
Summary: Facilitate clustering of similar URLs of a website
Home-page: https://github.com/daremon/urlclustering
Author: Dimitris Giannitsaros
Author-email: daremon@gmail.com
License: MIT
Keywords: cluster clustering urls
Platform: UNKNOWN
Classifier: Development Status :: 4 - Beta
Classifier: Environment :: Other Environment
Classifier: Intended Audience :: Developers
Classifier: License :: OSI Approved :: MIT License
Classifier: Operating System :: OS Independent
Classifier: Programming Language :: Python
Classifier: Programming Language :: Python :: 2
Classifier: Programming Language :: Python :: 2.7
Classifier: Programming Language :: Python :: 3
Classifier: Topic :: Internet
Classifier: Topic :: Software Development :: Libraries :: Python Modules
